trengine/__init__.py
trengine/exceptions.py
trengine/google.py
trengine/hozory.py
trengine/identify_music.py
trengine/ocr.py
trengine/speech_to_text.py
trengine/tdict.py
trengine/text_to_speech.py
trengine/tr.py
trengine/types.py
trengine-2.8.dist-info/LICENSE
trengine-2.8.dist-info/METADATA
trengine-2.8.dist-info/WHEEL
trengine-2.8.dist-info/top_level.txt
trengine-2.8.dist-info/RECORD
