Metadata-Version: 2.1
Name: trengine
Version: 2.8
Summary: TREngine is python library based on 4 translators engines
Author-email: ZAID <me@zaid.pro>
Project-URL: Homepage, https://github.com/2ei/trengine
Project-URL: Issues, https://github.com/2ei/trengine/issues
Classifier: Programming Language :: Python :: 3
Classifier: License :: OSI Approved :: MIT License
Classifier: Operating System :: OS Independent
Requires-Python: >=3.8
License-File: LICENSE
Requires-Dist: aiohttp
Requires-Dist: asyncio
Requires-Dist: requests
